{
  "timestamp": "2025-10-20T01:56:04.037Z",
  "summary": {
    "total": 4,
    "passed": 4,
    "failed": 0,
    "warnings": 0
  },
  "checks": [
    {
      "name": "生产环境检查",
      "script": "production-check",
      "description": "检查生产环境配置、健康检查端点、TypeScript 编译和环境变量",
      "success": true,
      "duration": 1623,
      "output": "\n> forever-paws-backend@1.0.0 production-check\n> node scripts/production-deploy-check.js\n\n🚀 Forever Paws 生产部署检查脚本\n=====================================\n\n\n📦 检查 package.json 配置...\n✅ package.json: /Users/junlish/Desktop/test/api/package.json\n✅ 脚本存在: start\n✅ 脚本存在: build\n✅ 脚本存在: dev\n✅ 脚本存在: test\n✅ 脚本存在: health-check\n✅ 脚本存在: production-check\n✅ Node.js 版本要求: >=18.0.0\n✅ 依赖存在: express\n✅ 依赖存在: @supabase/supabase-js\n✅ 依赖存在: cors\n✅ 依赖存在: helmet\n\n🚂 检查 Railway 配置...\n✅ railway.toml: /Users/junlish/Desktop/test/api/railway.toml\n✅ 健康检查路径已配置\n✅ NODE_ENV 环境变量已配置\n\n🔧 检查环境变量文件...\n✅ .env.example 模板文件: /Users/junlish/Desktop/test/api/.env.example\n✅ .env.production 生产配置: /Users/junlish/Desktop/test/api/.env.production\n⚠️  生产环境缺少以下环境变量: ALLOWED_ORIGINS, API_BASE_URL, DB_POOL_MIN, DB_POOL_MAX, DB_TIMEOUT, CACHE_TTL, ENABLE_MONITORING, MONITORING_ENDPOINT, FROM_EMAIL, SENTRY_DSN, DATADOG_API_KEY, STORAGE_BUCKET, CDN_URL, STRIPE_WEBHOOK_SECRET, FCM_SERVER_KEY, APNS_KEY_ID, APNS_TEAM_ID, DEBUG, MOCK_EXTERNAL_APIS\n\n📝 检查 TypeScript 配置...\n✅ tsconfig.json: /Users/junlish/Desktop/test/api/tsconfig.json\n✅ 输出目录: ./dist\n✅ 编译目标: ES2020\n\n🔨 检查构建过程...\n正在执行 TypeScript 编译检查...\n✅ TypeScript 编译检查通过\n\n🏥 检查健康检查端点...\n✅ 健康检查路由: /Users/junlish/Desktop/test/api/src/routes/health.ts\n✅ 健康检查端点已配置\n\n🔒 检查安全配置...\n✅ .gitignore: /Users/junlish/Desktop/test/api/.gitignore\n✅ .gitignore 包含: .env\n✅ .gitignore 包含: node_modules\n✅ .gitignore 包含: *.log\n✅ .gitignore 包含: .DS_Store\n⚠️  发现敏感文件: .env - 确保不会提交到版本控制\n\n🗄️ 检查数据库迁移文件...\n✅ 找到 24 个迁移文件\n  - 001_initial_schema.sql\n  - 002_add_missing_tables.sql\n  - 003_rls_policies.sql\n  - check_permissions.sql\n  - complete_rls_reset.sql\n  - create_enhanced_features_schema.sql\n  - create_forever_paws_schema.sql\n  - create_images_bucket.sql\n  - debug_rls_policies.sql\n  - extend_forever_paws_schema.sql\n  - fix_all_rls_policies_comprehensive.sql\n  - fix_family_groups_insert_policy.sql\n  - fix_family_groups_rls_policies.sql\n  - fix_pet_photos_rls_20250125.sql\n  - fix_pet_photos_rls_final.sql\n  - fix_pet_photos_rls_new.sql\n  - fix_pet_photos_rls_only.sql\n  - fix_pet_photos_rls_v2.sql\n  - fix_pet_photos_rls_v3.sql\n  - fix_user_profiles_rls_final.sql\n  - fix_users_rls_policy_final.sql\n  - fix_users_rls_policy_v3.sql\n  - open_rls_policies_completely.sql\n  - upgrade_forever_paws_features.sql\n✅ 找到 15 个 RLS 相关迁移文件\n\n📊 检查结果汇总\n==================\n\n⚠️  警告信息:\n1. 生产环境缺少环境变量: ALLOWED_ORIGINS, API_BASE_URL, DB_POOL_MIN, DB_POOL_MAX, DB_TIMEOUT, CACHE_TTL, ENABLE_MONITORING, MONITORING_ENDPOINT, FROM_EMAIL, SENTRY_DSN, DATADOG_API_KEY, STORAGE_BUCKET, CDN_URL, STRIPE_WEBHOOK_SECRET, FCM_SERVER_KEY, APNS_KEY_ID, APNS_TEAM_ID, DEBUG, MOCK_EXTERNAL_APIS\n2. 敏感文件 .env 存在，确保已添加到 .gitignore\n\n✅ 所有检查通过，可以进行生产部署！\n\n🚀 下一步部署建议:\n1. 确保所有环境变量已在 Railway Dashboard 中配置\n2. 运行数据库迁移: npm run db:migrate\n3. 部署到 Railway: git push origin main\n4. 验证部署: 访问健康检查端点\n5. 更新 iOS 应用的生产 API 端点\n",
      "error": "",
      "timestamp": "2025-10-20T01:55:59.736Z"
    },
    {
      "name": "数据库迁移检查",
      "script": "migration-check",
      "description": "分析 Supabase 迁移文件、RLS 策略和权限配置",
      "success": true,
      "duration": 230,
      "output": "\n> forever-paws-backend@1.0.0 migration-check\n> node scripts/database-migration-check.js\n\n🗄️ Forever Paws 数据库迁移检查脚本\n=====================================\n\n📁 检查迁移文件目录...\n✅ 迁移目录存在: /Users/junlish/Desktop/test/supabase/migrations\n✅ 找到 24 个迁移文件\n  - 001_initial_schema.sql (8873 bytes)\n  - 002_add_missing_tables.sql (9968 bytes)\n  - 003_rls_policies.sql (8138 bytes)\n  - check_permissions.sql (2451 bytes)\n  - complete_rls_reset.sql (2761 bytes)\n  - create_enhanced_features_schema.sql (6510 bytes)\n  - create_forever_paws_schema.sql (7353 bytes)\n  - create_images_bucket.sql (681 bytes)\n  - debug_rls_policies.sql (1556 bytes)\n  - extend_forever_paws_schema.sql (7103 bytes)\n  - fix_all_rls_policies_comprehensive.sql (4649 bytes)\n  - fix_family_groups_insert_policy.sql (906 bytes)\n  - fix_family_groups_rls_policies.sql (1709 bytes)\n  - fix_pet_photos_rls_20250125.sql (2243 bytes)\n  - fix_pet_photos_rls_final.sql (2243 bytes)\n  - fix_pet_photos_rls_new.sql (2243 bytes)\n  - fix_pet_photos_rls_only.sql (2243 bytes)\n  - fix_pet_photos_rls_v2.sql (2243 bytes)\n  - fix_pet_photos_rls_v3.sql (2243 bytes)\n  - fix_user_profiles_rls_final.sql (1753 bytes)\n  - fix_users_rls_policy_final.sql (1551 bytes)\n  - fix_users_rls_policy_v3.sql (1767 bytes)\n  - open_rls_policies_completely.sql (2163 bytes)\n  - upgrade_forever_paws_features.sql (6832 bytes)\n\n🔍 分析迁移文件内容...\n✅ SCHEMA 相关文件 (20个):\n  - 001_initial_schema.sql\n  - 002_add_missing_tables.sql\n  - 003_rls_policies.sql\n  - complete_rls_reset.sql\n  - create_enhanced_features_schema.sql\n  - create_forever_paws_schema.sql\n  - debug_rls_policies.sql\n  - extend_forever_paws_schema.sql\n  - fix_all_rls_policies_comprehensive.sql\n  - fix_pet_photos_rls_20250125.sql\n  - fix_pet_photos_rls_final.sql\n  - fix_pet_photos_rls_new.sql\n  - fix_pet_photos_rls_only.sql\n  - fix_pet_photos_rls_v2.sql\n  - fix_pet_photos_rls_v3.sql\n  - fix_user_profiles_rls_final.sql\n  - fix_users_rls_policy_final.sql\n  - fix_users_rls_policy_v3.sql\n  - open_rls_policies_completely.sql\n  - upgrade_forever_paws_features.sql\n✅ RLS 相关文件 (18个):\n  - 003_rls_policies.sql\n  - complete_rls_reset.sql\n  - create_enhanced_features_schema.sql\n  - create_forever_paws_schema.sql\n  - debug_rls_policies.sql\n  - extend_forever_paws_schema.sql\n  - fix_all_rls_policies_comprehensive.sql\n  - fix_pet_photos_rls_20250125.sql\n  - fix_pet_photos_rls_final.sql\n  - fix_pet_photos_rls_new.sql\n  - fix_pet_photos_rls_only.sql\n  - fix_pet_photos_rls_v2.sql\n  - fix_pet_photos_rls_v3.sql\n  - fix_user_profiles_rls_final.sql\n  - fix_users_rls_policy_final.sql\n  - fix_users_rls_policy_v3.sql\n  - open_rls_policies_completely.sql\n  - upgrade_forever_paws_features.sql\n✅ POLICIES 相关文件 (21个):\n  - 003_rls_policies.sql\n  - complete_rls_reset.sql\n  - create_enhanced_features_schema.sql\n  - create_forever_paws_schema.sql\n  - create_images_bucket.sql\n  - debug_rls_policies.sql\n  - extend_forever_paws_schema.sql\n  - fix_all_rls_policies_comprehensive.sql\n  - fix_family_groups_insert_policy.sql\n  - fix_family_groups_rls_policies.sql\n  - fix_pet_photos_rls_20250125.sql\n  - fix_pet_photos_rls_final.sql\n  - fix_pet_photos_rls_new.sql\n  - fix_pet_photos_rls_only.sql\n  - fix_pet_photos_rls_v2.sql\n  - fix_pet_photos_rls_v3.sql\n  - fix_user_profiles_rls_final.sql\n  - fix_users_rls_policy_final.sql\n  - fix_users_rls_policy_v3.sql\n  - open_rls_policies_completely.sql\n  - upgrade_forever_paws_features.sql\n✅ FUNCTIONS 相关文件 (4个):\n  - 001_initial_schema.sql\n  - 002_add_missing_tables.sql\n  - create_enhanced_features_schema.sql\n  - fix_user_profiles_rls_final.sql\n✅ TRIGGERS 相关文件 (4个):\n  - 001_initial_schema.sql\n  - 002_add_missing_tables.sql\n  - create_enhanced_features_schema.sql\n  - fix_user_profiles_rls_final.sql\n✅ INDEXES 相关文件 (6个):\n  - 001_initial_schema.sql\n  - 002_add_missing_tables.sql\n  - create_enhanced_features_schema.sql\n  - create_forever_paws_schema.sql\n  - extend_forever_paws_schema.sql\n  - upgrade_forever_paws_features.sql\n✅ PERMISSIONS 相关文件 (6个):\n  - 003_rls_policies.sql\n  - check_permissions.sql\n  - create_enhanced_features_schema.sql\n  - create_forever_paws_schema.sql\n  - extend_forever_paws_schema.sql\n  - upgrade_forever_paws_features.sql\n✅ DATA 相关文件 (23个):\n  - 001_initial_schema.sql\n  - 002_add_missing_tables.sql\n  - 003_rls_policies.sql\n  - check_permissions.sql\n  - complete_rls_reset.sql\n  - create_enhanced_features_schema.sql\n  - create_forever_paws_schema.sql\n  - create_images_bucket.sql\n  - debug_rls_policies.sql\n  - extend_forever_paws_schema.sql\n  - fix_all_rls_policies_comprehensive.sql\n  - fix_family_groups_rls_policies.sql\n  - fix_pet_photos_rls_20250125.sql\n  - fix_pet_photos_rls_final.sql\n  - fix_pet_photos_rls_new.sql\n  - fix_pet_photos_rls_only.sql\n  - fix_pet_photos_rls_v2.sql\n  - fix_pet_photos_rls_v3.sql\n  - fix_user_profiles_rls_final.sql\n  - fix_users_rls_policy_final.sql\n  - fix_users_rls_policy_v3.sql\n  - open_rls_policies_completely.sql\n  - upgrade_forever_paws_features.sql\n\n🔒 检查 RLS 策略完整性...\n✅ 找到 16 个 RLS 相关文件\n✅ users 表有 RLS 策略\n✅ user_profiles 表有 RLS 策略\n✅ pets 表有 RLS 策略\n✅ pet_photos 表有 RLS 策略\n✅ letters 表有 RLS 策略\n✅ orders 表有 RLS 策略\n\n👥 检查权限配置...\n✅ 找到 7 个权限配置文件:\n  - 003_rls_policies.sql\n  - check_permissions.sql\n  - create_enhanced_features_schema.sql\n  - create_forever_paws_schema.sql\n  - extend_forever_paws_schema.sql\n  - open_rls_policies_completely.sql\n  - upgrade_forever_paws_features.sql\n✅ 找到权限检查脚本: check_permissions.sql\n\n⚡ 检查迁移文件冲突...\n⚠️  表 if 在多个文件中创建: 002_add_missing_tables.sql, 002_add_missing_tables.sql, 002_add_missing_tables.sql, 002_add_missing_tables.sql, 002_add_missing_tables.sql, create_enhanced_features_schema.sql, create_enhanced_features_schema.sql, create_enhanced_features_schema.sql, create_enhanced_features_schema.sql, create_enhanced_features_schema.sql, extend_forever_paws_schema.sql, extend_forever_paws_schema.sql, extend_forever_paws_schema.sql, extend_forever_paws_schema.sql, extend_forever_paws_schema.sql, extend_forever_paws_schema.sql, extend_forever_paws_schema.sql, fix_user_profiles_rls_final.sql, upgrade_forever_paws_features.sql, upgrade_forever_paws_features.sql, upgrade_forever_paws_features.sql, upgrade_forever_paws_features.sql, upgrade_forever_paws_features.sql\n⚠️  表 public 在多个文件中创建: create_forever_paws_schema.sql, create_forever_paws_schema.sql, create_forever_paws_schema.sql, create_forever_paws_schema.sql, create_forever_paws_schema.sql, create_forever_paws_schema.sql, create_forever_paws_schema.sql, create_forever_paws_schema.sql\n⚠️  策略 family members can view family pets 在多个文件中创建: 003_rls_policies.sql, 003_rls_policies.sql\n⚠️  策略 users can view own profile 在多个文件中创建: create_forever_paws_schema.sql, extend_forever_paws_schema.sql\n⚠️  策略 users can update own profile 在多个文件中创建: create_forever_paws_schema.sql, extend_forever_paws_schema.sql\n⚠️  策略 users can insert own profile 在多个文件中创建: create_forever_paws_schema.sql, extend_forever_paws_schema.sql\n⚠️  策略 users can manage own pets 在多个文件中创建: create_forever_paws_schema.sql, extend_forever_paws_schema.sql\n⚠️  策略 users can manage own letters 在多个文件中创建: create_forever_paws_schema.sql, extend_forever_paws_schema.sql\n⚠️  策略 users can view own subscriptions 在多个文件中创建: create_forever_paws_schema.sql, extend_forever_paws_schema.sql\n⚠️  策略 users can manage own orders 在多个文件中创建: create_forever_paws_schema.sql, extend_forever_paws_schema.sql\n⚠️  策略 users can view own order items 在多个文件中创建: create_forever_paws_schema.sql, extend_forever_paws_schema.sql\n⚠️  策略 pet_photos_select_policy 在多个文件中创建: fix_all_rls_policies_comprehensive.sql, fix_pet_photos_rls_20250125.sql, fix_pet_photos_rls_final.sql, fix_pet_photos_rls_new.sql, fix_pet_photos_rls_only.sql, fix_pet_photos_rls_v2.sql, fix_pet_photos_rls_v3.sql\n⚠️  策略 pet_photos_insert_policy 在多个文件中创建: fix_all_rls_policies_comprehensive.sql, fix_pet_photos_rls_20250125.sql, fix_pet_photos_rls_final.sql, fix_pet_photos_rls_new.sql, fix_pet_photos_rls_only.sql, fix_pet_photos_rls_v2.sql, fix_pet_photos_rls_v3.sql\n⚠️  策略 pet_photos_update_policy 在多个文件中创建: fix_all_rls_policies_comprehensive.sql, fix_pet_photos_rls_20250125.sql, fix_pet_photos_rls_final.sql, fix_pet_photos_rls_new.sql, fix_pet_photos_rls_only.sql, fix_pet_photos_rls_v2.sql, fix_pet_photos_rls_v3.sql\n⚠️  策略 pet_photos_delete_policy 在多个文件中创建: fix_all_rls_policies_comprehensive.sql, fix_pet_photos_rls_20250125.sql, fix_pet_photos_rls_final.sql, fix_pet_photos_rls_new.sql, fix_pet_photos_rls_only.sql, fix_pet_photos_rls_v2.sql, fix_pet_photos_rls_v3.sql\n⚠️  策略 users_insert_policy 在多个文件中创建: fix_users_rls_policy_final.sql, fix_users_rls_policy_v3.sql\n⚠️  策略 users_select_policy 在多个文件中创建: fix_users_rls_policy_final.sql, fix_users_rls_policy_v3.sql\n⚠️  策略 users_update_policy 在多个文件中创建: fix_users_rls_policy_final.sql, fix_users_rls_policy_v3.sql\n⚠️  策略 users_delete_policy 在多个文件中创建: fix_users_rls_policy_final.sql, fix_users_rls_policy_v3.sql\n\n📋 生成迁移执行计划...\n建议的迁移执行顺序:\n1. 001_initial_schema.sql\n2. create_enhanced_features_schema.sql\n3. create_forever_paws_schema.sql\n4. extend_forever_paws_schema.sql\n5. 002_add_missing_tables.sql\n6. extend_forever_paws_schema.sql\n7. upgrade_forever_paws_features.sql\n8. 003_rls_policies.sql\n9. complete_rls_reset.sql\n10. debug_rls_policies.sql\n11. open_rls_policies_completely.sql\n12. fix_all_rls_policies_comprehensive.sql\n13. fix_family_groups_insert_policy.sql\n14. fix_family_groups_rls_policies.sql\n15. fix_pet_photos_rls_20250125.sql\n16. fix_pet_photos_rls_final.sql\n17. fix_pet_photos_rls_new.sql\n18. fix_pet_photos_rls_only.sql\n19. fix_pet_photos_rls_v2.sql\n20. fix_pet_photos_rls_v3.sql\n21. fix_user_profiles_rls_final.sql\n22. fix_users_rls_policy_final.sql\n23. fix_users_rls_policy_v3.sql\n24. check_permissions.sql\n25. create_images_bucket.sql\n\n📊 迁移检查结果汇总\n====================\n\n📈 统计信息:\n- 总迁移文件数: 24\n- RLS 相关文件: 39\n- 架构文件: 20\n- 权限文件: 6\n\n⚠️  警告信息:\n1. 表 if 可能存在重复创建\n2. 表 public 可能存在重复创建\n3. 策略 family members can view family pets 可能存在重复创建\n4. 策略 users can view own profile 可能存在重复创建\n5. 策略 users can update own profile 可能存在重复创建\n6. 策略 users can insert own profile 可能存在重复创建\n7. 策略 users can manage own pets 可能存在重复创建\n8. 策略 users can manage own letters 可能存在重复创建\n9. 策略 users can view own subscriptions 可能存在重复创建\n10. 策略 users can manage own orders 可能存在重复创建\n11. 策略 users can view own order items 可能存在重复创建\n12. 策略 pet_photos_select_policy 可能存在重复创建\n13. 策略 pet_photos_insert_policy 可能存在重复创建\n14. 策略 pet_photos_update_policy 可能存在重复创建\n15. 策略 pet_photos_delete_policy 可能存在重复创建\n16. 策略 users_insert_policy 可能存在重复创建\n17. 策略 users_select_policy 可能存在重复创建\n18. 策略 users_update_policy 可能存在重复创建\n19. 策略 users_delete_policy 可能存在重复创建\n\n✅ 数据库迁移文件检查通过！\n\n🚀 下一步建议:\n1. 在生产环境执行迁移前，先在测试环境验证\n2. 按照建议的顺序执行迁移文件\n3. 执行迁移后验证 RLS 策略是否正常工作\n4. 检查所有表的权限配置\n5. 运行权限检查脚本验证访问控制\n",
      "error": "",
      "timestamp": "2025-10-20T01:55:59.967Z"
    },
    {
      "name": "安全审计",
      "script": "security-audit",
      "description": "检查环境变量安全、代码安全、API 安全和配置安全",
      "success": true,
      "duration": 189,
      "output": "\n> forever-paws-backend@1.0.0 security-audit\n> node scripts/security-audit.js\n\n🔒 Forever Paws 安全审计开始\n====================================\n\n🔐 环境变量安全检查\n----------------------\n⚠️ .env 敏感信息检查: 发现可能的明文敏感信息\n✅ .env 文件权限\n⚠️ .env.production 敏感信息检查: 发现可能的明文敏感信息\n✅ .env.production 文件权限\n✅ .env 文件 Git 忽略\n\n📦 依赖安全检查\n------------------\n✅ 已知漏洞依赖检查\n✅ 依赖版本固定\n\n💻 代码安全检查\n------------------\n⚠️ 生产环境 console.log: 代码中存在 console.log 语句\n✅ eval() 使用检查\n✅ 硬编码密钥检查\n\n🌐 API 安全检查\n------------------\n⚠️ API 速率限制: 未发现速率限制配置\n✅ API 输入验证\n✅ API 认证机制\n✅ API 错误处理\n\n🗄️  数据库安全检查\n--------------------\n✅ 数据库 RLS 策略\n✅ 数据库权限配置\n✅ 数据库索引优化\n\n⚙️  配置文件安全检查\n----------------------\n✅ Railway 健康检查配置\n✅ Railway 构建配置\n✅ package.json 安全脚本\n\n📊 生成安全报告\n------------------\n✅ 安全报告已生成: /Users/junlish/Desktop/test/api/reports/security-audit-1760925360152.json\n\n🎯 安全审计结果汇总\n======================\n✅ 通过: 16\n❌ 失败: 0\n⚠️  警告: 4\n🚨 关键: 0\n🎚️  风险等级: MEDIUM\n⏱️  耗时: 9ms\n\n💡 安全建议:\n   💡 处理安全警告，提高系统安全性\n   💡 定期更新依赖包，修复已知漏洞\n   💡 实施定期安全审计和渗透测试\n   ℹ️ 配置安全监控和告警系统\n\n🚀 部署建议:\n   ✅ 可以部署：建议处理警告项以提高安全性\n",
      "error": "",
      "timestamp": "2025-10-20T01:56:00.156Z"
    },
    {
      "name": "部署检查清单",
      "script": "deployment-checklist",
      "description": "综合检查项目配置、环境设置、代码质量和部署就绪度",
      "success": true,
      "duration": 3881,
      "output": "\n> forever-paws-backend@1.0.0 deployment-checklist\n> node scripts/deployment-checklist.js\n\n📋 Forever Paws 部署检查清单\n====================================\n\n🔍 开始执行检查...\n\n📂 项目配置\n────────\n  ✅ package.json 存在且有效\n  ✅ Railway 配置文件\n  ✅ TypeScript 配置\n\n📂 环境配置\n────────\n  ✅ 生产环境变量文件\n  ✅ 环境变量模板\n  ✅ Git 忽略配置\n\n📂 代码质量\n────────\n  ✅ TypeScript 编译\n  ⚠️ ESLint 检查: ESLint 检查失败\n\n📂 依赖管理\n────────\n  ✅ node_modules 存在\n  ✅ package-lock.json 存在\n  ✅ 安全漏洞检查\n\n📂 API 配置\n──────────\n  ✅ 健康检查端点\n  ✅ 主路由配置\n  ✅ 中间件配置\n\n📂 数据库配置\n─────────\n  ✅ Supabase 迁移文件: 发现 24 个迁移文件\n  ✅ RLS 策略文件: 发现 16 个 RLS 文件\n\n📂 构建部署\n────────\n  ✅ 构建脚本存在\n  ✅ 启动脚本存在\n  ✅ 生产检查脚本\n\n📂 安全配置\n────────\n  ✅ 敏感文件保护\n  ✅ 生产环境配置\n\n📂 监控日志\n────────\n  ✅ 日志目录配置\n  ✅ 监控配置脚本\n\n📂 文档说明\n────────\n  ✅ README 文件\n  ✅ 部署文档\n\n📊 检查结果汇总\n==================\n✅ 通过: 24\n❌ 失败: 0\n⚠️  警告: 1\n🚨 关键: 0\n📊 总计: 25\n\n🟢 部署就绪度: READY (96%)\n💬 已准备好部署到生产环境\n\n⚠️  建议处理的警告:\n\n  📂 代码质量:\n    ⚠️  ESLint 检查: ESLint 检查失败\n\n📄 详细报告已保存: /Users/junlish/Desktop/test/api/reports/deployment-checklist-1760925364033.json\n\n⏱️  检查耗时: 3704ms\n",
      "error": "",
      "timestamp": "2025-10-20T01:56:04.037Z"
    }
  ],
  "recommendations": [
    {
      "priority": "info",
      "message": "所有检查都已通过，可以安全部署到生产环境"
    },
    {
      "priority": "medium",
      "message": "在生产环境部署前，建议在测试环境进行完整验证"
    },
    {
      "priority": "medium",
      "message": "部署后监控应用性能和错误日志"
    },
    {
      "priority": "low",
      "message": "定期运行安全审计和依赖更新"
    }
  ],
  "deploymentReadiness": {
    "level": "READY",
    "score": 100,
    "message": "所有检查通过，已准备好部署到生产环境",
    "canDeploy": true,
    "passedChecks": 4,
    "failedChecks": 0,
    "totalChecks": 4
  }
}